flame_models/__init__.py
flame_models/apriori.py
flame_models/gaussian_mixture_model.py
flame_models/genetic_algorithm.py
flame_models/k_means.py
flame_models/partitioning_around_medoids.py
flame_models/principal_component_analysis.py
flame_model_a-1.0.0.dist-info/LICENSE.txt
flame_model_a-1.0.0.dist-info/METADATA
flame_model_a-1.0.0.dist-info/WHEEL
flame_model_a-1.0.0.dist-info/top_level.txt
flame_model_a-1.0.0.dist-info/RECORD
